[
  {
    "anomaly_length": {
      "max": 200,
      "median": 200,
      "min": 200
    },
    "contamination": 0.003563601375550131,
    "dataset_id": [
      "KDD-TSAD",
      "070_UCR_Anomaly_DISTORTEDltstdbs30791AI"
    ],
    "dimensions": 1,
    "is_train": false,
    "length": 56123,
    "means": {
      "value": -0.4385225321440692
    },
    "num_anomalies": 1,
    "periods": {
      "value": 91
    },
    "stationarities": {
      "value": "difference_stationary"
    },
    "stddevs": {
      "value": 41.91295774546631
    },
    "trends": {
      "value": []
    }
  },
  {
    "anomaly_length": {
      "max": 0,
      "median": 0,
      "min": 0
    },
    "contamination": 0.0,
    "dataset_id": [
      "KDD-TSAD",
      "070_UCR_Anomaly_DISTORTEDltstdbs30791AI"
    ],
    "dimensions": 1,
    "is_train": true,
    "length": 17555,
    "means": {
      "value": -0.15848032724593983
    },
    "num_anomalies": 0,
    "periods": {
      "value": 83
    },
    "stationarities": {
      "value": "difference_stationary"
    },
    "stddevs": {
      "value": 41.83871682338061
    },
    "trends": {
      "value": []
    }
  }
]